tests/__init__.py
tests/test_flags.py
tests/utils/__init__.py
tests/utils/test_fileutil.py
tinyenv/__init__.py
tinyenv/flags.py
tinyenv/utils/__init__.py
tinyenv/utils/fileutil.py
tinyenv-0.1.0.dist-info/DESCRIPTION.rst
tinyenv-0.1.0.dist-info/METADATA
tinyenv-0.1.0.dist-info/RECORD
tinyenv-0.1.0.dist-info/WHEEL
tinyenv-0.1.0.dist-info/metadata.json
tinyenv-0.1.0.dist-info/top_level.txt
